hivetracered/__init__.py
hivetracered/__main__.py
hivetracered/report.py
hivetracered/attacks/__init__.py
hivetracered/attacks/algo_attack.py
hivetracered/attacks/base_attack.py
hivetracered/attacks/composed_attack.py
hivetracered/attacks/model_attack.py
hivetracered/attacks/template_attack.py
hivetracered/attacks/types/__init__.py
hivetracered/attacks/types/context_switching/__init__.py
hivetracered/attacks/types/context_switching/dashed_divider_attack.py
hivetracered/attacks/types/context_switching/forget_everything_before_attack.py
hivetracered/attacks/types/context_switching/ignore_previous_instructions_attack.py
hivetracered/attacks/types/context_switching/symbol_divider_attack.py
hivetracered/attacks/types/in_context_learning/__init__.py
hivetracered/attacks/types/in_context_learning/few_shot_json_attack.py
hivetracered/attacks/types/in_context_learning/many_shot_jailbreak_attack.py
hivetracered/attacks/types/irrelevant_information/__init__.py
hivetracered/attacks/types/irrelevant_information/distractors_attack.py
hivetracered/attacks/types/irrelevant_information/distractors_negated_attack.py
hivetracered/attacks/types/irrelevant_information/irrelevant_information_attack.py
hivetracered/attacks/types/output_formatting/__init__.py
hivetracered/attacks/types/output_formatting/base64_output_attack.py
hivetracered/attacks/types/output_formatting/csv_output_attack.py
hivetracered/attacks/types/output_formatting/json_output_attack.py
hivetracered/attacks/types/output_formatting/language_output_attack.py
hivetracered/attacks/types/output_formatting/prefix_injection_attack.py
hivetracered/attacks/types/output_formatting/prefix_injection_of_course_attack.py
hivetracered/attacks/types/output_formatting/refusal_suppression_attack.py
hivetracered/attacks/types/output_formatting/gradient_methods/__init__.py
hivetracered/attacks/types/output_formatting/gradient_methods/gcg_transfer_harmbench_attack.py
hivetracered-1.0.8.dist-info/licenses/LICENSE
hivetracered-1.0.8.dist-info/METADATA
hivetracered-1.0.8.dist-info/WHEEL
hivetracered-1.0.8.dist-info/entry_points.txt
hivetracered-1.0.8.dist-info/top_level.txt
hivetracered-1.0.8.dist-info/RECORD
