Metadata-Version: 2.4
Name: hivetracered
Version: 1.0.8
Summary: LLM Red Teaming Framework for defensive security research
Author-email: HiveTrace <sales@raftds.com>
License: Apache-2.0
Project-URL: Homepage, https://github.com/HiveTrace/HiveTraceRed
Project-URL: Documentation, https://hivetrace.github.io/HiveTraceRed/
Project-URL: Repository, https://github.com/HiveTrace/HiveTraceRed
Project-URL: Issues, https://github.com/HiveTrace/HiveTraceRed/issues
Keywords: llm,red-team,security,testing,adversarial,ai-safety
Classifier: Intended Audience :: Developers
Classifier: Intended Audience :: Science/Research
Classifier: License :: OSI Approved :: Apache Software License
Classifier: Programming Language :: Python :: 3
Classifier: Programming Language :: Python :: 3.10
Classifier: Programming Language :: Python :: 3.11
Classifier: Programming Language :: Python :: 3.12
Classifier: Programming Language :: Python :: 3.13
Classifier: Topic :: Security
Classifier: Topic :: Scientific/Engineering :: Artificial Intelligence
Requires-Python: >=3.10
License-File: LICENSE
Requires-Dist: pandas<3.0.0,>=2.0.0
Requires-Dist: pyarrow<20.0.0,>=17.0.0
Requires-Dist: pyyaml<7.0,>=6.0
Requires-Dist: python-dotenv<2.0.0,>=1.0.0
Requires-Dist: tqdm<5.0.0,>=4.65.0
Requires-Dist: aiohttp<4.0.0,>=3.8.0
Requires-Dist: requests<3.0.0,>=2.28.0
Requires-Dist: langchain<1.0.0,>=0.3.27
Requires-Dist: langchain-core<0.4.0,>=0.3.72
Requires-Dist: langchain-community<0.4.0,>=0.3.27
Requires-Dist: langchain-openai<0.3.0,>=0.2.0
Requires-Dist: langchain-ollama<0.4.0,>=0.3.0
Requires-Dist: langchain-gigachat<1.0.0,>=0.3.0
Requires-Dist: langchain-google-genai<3.0.0,>=2.1.0
Requires-Dist: google-genai<2.0.0,>=1.0.0
Requires-Dist: yandex-cloud-ml-sdk<1.0.0,>=0.1.0
Requires-Dist: cyrtranslit<2.0.0,>=1.2.0
Requires-Dist: plotly<6.0.0,>=5.0.0
Requires-Dist: numpy<3.0.0,>=1.24.0
Provides-Extra: dev
Requires-Dist: build>=1.3.0; extra == "dev"
Requires-Dist: twine>=6.0.0; extra == "dev"
Provides-Extra: docs
Requires-Dist: sphinx>=5.0.0; extra == "docs"
Requires-Dist: sphinx-autodoc-typehints>=1.22.0; extra == "docs"
Requires-Dist: furo>=2023.3.27; extra == "docs"
Requires-Dist: roman>=5.0; extra == "docs"
Provides-Extra: web
Requires-Dist: playwright>=1.57.0; extra == "web"
Requires-Dist: nest_asyncio>=1.6.0; extra == "web"
Provides-Extra: all
Requires-Dist: hivetracered[dev,docs,web]; extra == "all"
Dynamic: license-file
